cses/__init__.py
cses/__main__.py
cses/generator.py
cses/parser.py
cses/types.py
pycses-0.1.2.dist-info/licenses/LICENSE
pycses-0.1.2.dist-info/METADATA
pycses-0.1.2.dist-info/WHEEL
pycses-0.1.2.dist-info/top_level.txt
pycses-0.1.2.dist-info/RECORD
