Metadata-Version: 2.4
Name: pycses
Version: 0.1.2
Summary: CSES access framework for Python
Home-page: https://github.com/SmartTeachCN/pycses
Author: SmartTeachCN
Author-email: unDefFtr <contact@smart-teach.cn>
License: MIT
Project-URL: Homepage, https://github.com/SmartTeachCN/pycses
Classifier: Programming Language :: Python :: 3
Classifier: License :: OSI Approved :: MIT License
Classifier: Operating System :: OS Independent
Requires-Python: >=3.6
License-File: LICENSE
Requires-Dist: PyYAML>=5.4.1
Dynamic: author
Dynamic: home-page
Dynamic: license-file
Dynamic: requires-python
